janusmskit/__init__.py
janusmskit/cloud/aws/kms.py
janusmskit/cmd/__init__.py
janusmskit/cmd/main.py
janusmskit/config/__init__.py
janusmskit/config/conf.py
janusmskit/config/confile.py
janusmskit/config/resource.py
janusmskit/constants.py
janusmskit/crypt/__init__.py
janusmskit/crypt/driver.py
janusmskit/crypt/fernet.py
janusmskit/exceptions.py
janusmskit/flask/__init__.py
janusmskit/flask/app/__init__.py
janusmskit/flask/app/create_app.py
janusmskit/flask/app/create_config.py
janusmskit/flask/app/utils.py
janusmskit/flask/configreload/__init__.py
janusmskit/flask/configreload/configreload.py
janusmskit/flask/healthcheck/__init__.py
janusmskit/flask/healthcheck/healthcheck.py
janusmskit/flask/services/__init__.py
janusmskit/flask/services/driver.py
janusmskit/flask/services/metrics.py
janusmskit/flask/services/requests.py
janusmskit/flask/services/service_discovery.py
janusmskit/flask/services/swagger.py
janusmskit/flask/services/tracer.py
janusmskit/logger/__init__.py
janusmskit/logger/logger.py
janusmskit/utils/__init__.py
janusmskit/utils/files.py
janusmskit/utils/utils.py
janusmskit-1.2.0.dist-info/LICENSE
janusmskit-1.2.0.dist-info/WHEEL
janusmskit-1.2.0.dist-info/METADATA
janusmskit-1.2.0.dist-info/RECORD
