Metadata-Version: 2.1
Name: janusmskit
Version: 1.2.0
Summary: Library of utils to create REST Python Microservices
Home-page: https://python-microservices.github.io/
License: GPL-3.0-only
Author: avara1986
Author-email: a.vara.1986@gmail.com
Requires-Python: >=3.6.1,<4.0
Classifier: Development Status :: 4 - Beta
Classifier: Framework :: Flask
Classifier: Intended Audience :: Developers
Classifier: License :: OSI Approved :: GNU General Public License v3 (GPLv3)
Classifier: Natural Language :: English
Classifier: Operating System :: OS Independent
Classifier: Programming Language :: Python
Classifier: Programming Language :: Python :: 3
Classifier: Programming Language :: Python :: 3 :: Only
Classifier: Programming Language :: Python :: 3.10
Classifier: Programming Language :: Python :: 3.6
Classifier: Programming Language :: Python :: 3.7
Classifier: Programming Language :: Python :: 3.8
Classifier: Programming Language :: Python :: 3.9
Classifier: Topic :: Internet :: WWW/HTTP
Classifier: Topic :: Software Development :: Libraries :: Application Frameworks
Classifier: Topic :: Software Development :: Libraries :: Python Modules
Provides-Extra: requests
Requires-Dist: Flask-OpenTracing (>=1.1.0,<2.0.0)
Requires-Dist: anyconfig (>=0.10.1)
Requires-Dist: boto3 (>=1.18.36,<2.0.0)
Requires-Dist: connexion (>=2.9.0,<3.0.0)
Requires-Dist: cryptography (>=3.4.7)
Requires-Dist: flask (>=1.1.4)
Requires-Dist: jaeger-client (>=4.6.1,<5.0.0)
Requires-Dist: opentracing (>=2.4.0,<3.0.0)
Requires-Dist: opentracing-instrumentation (>=3.3.1,<4.0.0)
Requires-Dist: prance (>=0.21.8,<0.22.0)
Requires-Dist: prometheus-client (>=0.11.0,<0.12.0)
Requires-Dist: py-ms-consulate (>=1.0.0,<2.0.0)
Requires-Dist: python-json-logger (>=2.0.0)
Requires-Dist: pyyaml (>=5.3.1)
Requires-Dist: requests (>=2.26.0,<3.0.0); extra == "requests"
Requires-Dist: semver (>=2.13.0,<3.0.0)
Requires-Dist: swagger-ui-bundle (>=0.0.8,<0.0.9)
Project-URL: Documentation, https://python-microservices.github.io/
Project-URL: Repository, https://github.com/AzadOpenSoft22/janus.git
